smart_append_path/__init__.py
smart_append_path-0.0.1.dist-info/METADATA
smart_append_path-0.0.1.dist-info/RECORD
smart_append_path-0.0.1.dist-info/WHEEL
smart_append_path-0.0.1.dist-info/top_level.txt
