Metadata-Version: 2.1
Name: smart-append-path
Version: 0.0.1
Summary: A small import package
Home-page: https://github.com/lua511/py_smart_append_path.git
Author: duanping
Author-email: liuan.yla@alibaba-inc.com
License: UNKNOWN
Platform: UNKNOWN
Classifier: Programming Language :: Python :: 2
Classifier: License :: OSI Approved :: MIT License
Classifier: Operating System :: OS Independent
